qz7_hello.py
qz7_hello-0.1.dist-info/WHEEL
qz7_hello-0.1.dist-info/METADATA
qz7_hello-0.1.dist-info/RECORD
