Metadata-Version: 2.1
Name: qz7_hello
Version: 0.1
Summary: qz7 hello.
Home-page: https://github.com/parantapa/qz7_hello
License: UNKNOWN
Author: Parantapa Bhattacharya
Author-email: pb@parantapa.net
Classifier: License :: OSI Approved :: MIT License
